apgsa/__init__.py
apgsa/pg.py
apgsa/utils.py
apgsa/version.py
apgsa-0.0.5.dist-info/LICENSE
apgsa-0.0.5.dist-info/METADATA
apgsa-0.0.5.dist-info/WHEEL
apgsa-0.0.5.dist-info/top_level.txt
apgsa-0.0.5.dist-info/RECORD
